__init__.py
nfca/__init__.py
nfca/main.py
nfca-0.1.0.dist-info/METADATA
nfca-0.1.0.dist-info/WHEEL
nfca-0.1.0.dist-info/top_level.txt
nfca-0.1.0.dist-info/RECORD
