Metadata-Version: 2.4
Name: nfca
Version: 0.1.0
Summary: Simple Project for Demonstration Purposes
Requires-Python: >=3.11
Requires-Dist: numpy>=2.3.3
Requires-Dist: pygame>=2.6.1
Requires-Dist: rich>=14.1.0
Requires-Dist: torch>=2.8.0
